alphalogic_api3/__init__.py
alphalogic_api3/attributes.py
alphalogic_api3/conf_inspector.py
alphalogic_api3/decorators.py
alphalogic_api3/exceptions.py
alphalogic_api3/logger.py
alphalogic_api3/manager.py
alphalogic_api3/multistub.py
alphalogic_api3/options.py
alphalogic_api3/tasks_pool.py
alphalogic_api3/utils.py
alphalogic_api3/objects/__init__.py
alphalogic_api3/objects/command.py
alphalogic_api3/objects/event.py
alphalogic_api3/objects/object.py
alphalogic_api3/objects/parameter.py
alphalogic_api3/protocol/__init__.py
alphalogic_api3/protocol/rpc_pb2.py
alphalogic_api3/protocol/rpc_pb2_grpc.py
alphalogic_api3/tests/__init__.py
alphalogic_api3/tests/api_test.py
alphalogic_api3/tests/handlers_test.py
alphalogic_api3/tests/test2.py
alphalogic_api3-0.1.14.dist-info/LICENSE
alphalogic_api3-0.1.14.dist-info/METADATA
alphalogic_api3-0.1.14.dist-info/WHEEL
alphalogic_api3-0.1.14.dist-info/top_level.txt
alphalogic_api3-0.1.14.dist-info/RECORD
