Metadata-Version: 2.1
Name: alphalogic-api3
Version: 0.1.14
Summary: Python3 stub library for Alphalogic adapters.
Home-page: https://github.com/Alphaopen/alphalogic_api3
Author: Alphaopen
Author-email: mo@alphaopen.com
License: MIT
Platform: linux2
Platform: win32
Classifier: Programming Language :: Python
Classifier: Programming Language :: Python :: 3
Classifier: Programming Language :: Python :: 3 :: Only
Classifier: Programming Language :: Python :: 3.8
Classifier: Programming Language :: Python :: 3.9
Classifier: Programming Language :: Python :: 3.10
Classifier: Programming Language :: Python :: 3.11
Classifier: License :: OSI Approved :: MIT License
Classifier: Operating System :: OS Independent
Requires-Python: >=3.8
License-File: LICENSE
Requires-Dist: grpcio (~=1.51.1)
Requires-Dist: grpcio-tools (~=1.51.1)
Requires-Dist: distro
